{
"-Mb8ucPzRWgbjXeovmEF":{"userID":1,"venueID":"Jeniece","location":"9 Sommers Lane","time":"3/10/2021","details":"cubilia curae mauris viverra diam vitae quam suspendisse potenti nullam porttitor lacus"},
"-Mb8ucQ-AsJxbqVMRFZA":{"userID":2,"venueID":"Tobin","location":"7 Longview Way","time":"4/25/2021","details":"ullamcorper augue a suscipit nulla elit ac nulla sed vel enim sit amet nunc viverra dapibus nulla"},
"-Mb8ucQ1YJnE6ItBpAz1":{"userID":3,"venueID":"Katharina","location":"0291 Lindbergh Trail","time":"6/16/2020","details":"et eros vestibulum ac est lacinia nisi venenatis tristique fusce congue diam id ornare"},
"-Mb8ucQ2a5gR_X-ccwrL":{"userID":4,"venueID":"Stefania","location":"0 Cardinal Pass","time":"5/19/2021","details":"sapien cum sociis natoque penatibus et magnis dis parturient montes nascetur"},
"-Mb8ucQ49UArX05EvML7":{"userID":5,"venueID":"Reinaldo","location":"56 Nancy Lane","time":"8/25/2020","details":"vitae nisl aenean lectus pellentesque eget nunc donec quis orci eget orci vehicula"}
}